fenicsx_ldrb-0.1.18.dist-info/licenses/LICENSE
ldrb/__init__.py
ldrb/__main__.py
ldrb/aha.py
ldrb/calculus.py
ldrb/cli.py
ldrb/io.py
ldrb/ldrb.py
ldrb/utils.py
fenicsx_ldrb-0.1.18.dist-info/METADATA
fenicsx_ldrb-0.1.18.dist-info/WHEEL
fenicsx_ldrb-0.1.18.dist-info/entry_points.txt
fenicsx_ldrb-0.1.18.dist-info/top_level.txt
fenicsx_ldrb-0.1.18.dist-info/RECORD
