Metadata-Version: 2.4
Name: fenicsx-ldrb
Version: 0.1.18
Summary: Laplace-Dirichlet Rule-based algorithm for assigning myocardial fiber orientations.
Author-email: Henrik Finsberg <henriknf@simula.no>
License: MIT
Project-URL: Homepage, https://finsberg.github.io/fenicsx-ldrb
Project-URL: Documentation, https://finsberg.github.io/fenicsx-ldrb
Project-URL: Source, https://github.com/finsberg/fenicsx-ldrb
Project-URL: Tracker, https://github.com/finsberg/fenicsx-ldrb/issues
Keywords: cardiac,electrophysiology
Requires-Python: >=3.8
License-File: LICENSE
Requires-Dist: numpy
Requires-Dist: numba
Requires-Dist: adios4dolfinx
Requires-Dist: scipy
Provides-Extra: test
Requires-Dist: pytest; extra == "test"
Requires-Dist: pytest-cov; extra == "test"
Requires-Dist: cardiac-geometriesx; extra == "test"
Requires-Dist: scifem; extra == "test"
Requires-Dist: ukb-atlas; extra == "test"
Requires-Dist: pyvista; extra == "test"
Provides-Extra: dev
Requires-Dist: pdbpp; extra == "dev"
Requires-Dist: ipython; extra == "dev"
Requires-Dist: bump2version; extra == "dev"
Requires-Dist: pre-commit; extra == "dev"
Provides-Extra: pypi
Requires-Dist: twine; extra == "pypi"
Requires-Dist: build; extra == "pypi"
Provides-Extra: demos
Requires-Dist: cardiac-geometriesx; extra == "demos"
Provides-Extra: docs
Requires-Dist: jupyter-book<2.0; extra == "docs"
Requires-Dist: jupytext; extra == "docs"
Requires-Dist: pyvista[all]; extra == "docs"
Requires-Dist: fenicsx-ldrb[demos]; extra == "docs"
Provides-Extra: all
Requires-Dist: fenicsx-ldrb[test]; extra == "all"
Requires-Dist: fenicsx-ldrb[docs]; extra == "all"
Requires-Dist: fenicsx-ldrb[pypi]; extra == "all"
Requires-Dist: fenicsx-ldrb[dev]; extra == "all"
Requires-Dist: fenicsx-ldrb[demos]; extra == "all"
Dynamic: license-file
